{
  "configVersion": 1,
  "index": "/index.html",
  "assetGroups": [
    {
      "name": "app",
      "installMode": "prefetch",
      "updateMode": "prefetch",
      "urls": [
        "/favicon.ico",
        "/index.html",
        "/inline.da111741a681635e3e7a.bundle.js",
        "/main.6a71347138ea24500340.bundle.js",
        "/polyfills.c7d90cb5deaaa83e1e9f.bundle.js",
        "/styles.8165fa12f002b42458ca.bundle.css"
      ],
      "patterns": []
    },
    {
      "name": "assets",
      "installMode": "lazy",
      "updateMode": "prefetch",
      "urls": [],
      "patterns": []
    }
  ],
  "dataGroups": [],
  "hashTable": {
    "/inline.da111741a681635e3e7a.bundle.js": "fe203e2c1d8b2d8e47ed75eb083f8ed70024bfe6",
    "/main.6a71347138ea24500340.bundle.js": "5faef640d9951f859552e078f43a87492bb668ae",
    "/polyfills.c7d90cb5deaaa83e1e9f.bundle.js": "74cf4d580da28bb7c2c2cc03f482c09df6b920dd",
    "/styles.8165fa12f002b42458ca.bundle.css": "83f1dcf31318b68467c23d0c413b189925efff26",
    "/favicon.ico": "54e5858ba7475f82058d474e919c878182f99e19",
    "/index.html": "e3ef5defa2c4a97a1d5ff39ed68c5c0cde4cbfdf"
  }
}